rest_api_auth_manager/__init__.py
rest_api_auth_manager/config.py
rest_api_auth_manager/repository.py
rest_api_auth_manager-1.0.4.dist-info/LICENSE
rest_api_auth_manager-1.0.4.dist-info/METADATA
rest_api_auth_manager-1.0.4.dist-info/WHEEL
rest_api_auth_manager-1.0.4.dist-info/top_level.txt
rest_api_auth_manager-1.0.4.dist-info/RECORD
