Metadata-Version: 2.1
Name: rest-api-auth-manager
Version: 1.0.4
Summary: Simple manager for REST API authentication and authorization (token based)
Author-email: gxara <gabrielxara@gmail.com>
Project-URL: Homepage, https://github.com/gxara/rest_api_auth_manager
Project-URL: Bug Tracker, https://github.com/gxara/rest_api_auth_manager/issues
Classifier: Programming Language :: Python :: 3
Classifier: License :: OSI Approved :: MIT License
Classifier: Operating System :: OS Independent
Requires-Python: >=3.7
License-File: LICENSE
